autopi/__init__.py
autopi/autopi.py
autopi-0.0.1.dist-info/licenses/LICENSE
autopi-0.0.1.dist-info/METADATA
autopi-0.0.1.dist-info/WHEEL
autopi-0.0.1.dist-info/top_level.txt
autopi-0.0.1.dist-info/RECORD
