Metadata-Version: 2.4
Name: AutoPI
Version: 0.0.1
Summary: AutoPI is a python project, based on tkinter module to manipulate auto mouse movement and switching between tabs on your chrome browser. In case you need to keep up window active, you can use this application. It will move mouse and press keyboard shortcut to make window active and switching tabs.
Author-email: Mobarak Hosen Shakil <mh.ice.iu@gmail.com>, Sumaiya Shakil <ss130523@gmail.com>
License: GPL-3.0-or-later
Project-URL: Homepage, https://github.com/imShakil/autopi
Project-URL: Issues, https://github.com/imShakil/autopi/issues
Classifier: Programming Language :: Python :: 3
Classifier: Operating System :: OS Independent
Requires-Python: >=3.10
License-File: LICENSE
Dynamic: license-file
